README.md
pyproject.toml
setup.cfg
setup.py
caddiepy/__init__.py
caddiepy/api.py
caddiepy/pipeline.py
caddiepy/settings.py
caddiepy/task.py
caddiepy.egg-info/PKG-INFO
caddiepy.egg-info/SOURCES.txt
caddiepy.egg-info/dependency_links.txt
caddiepy.egg-info/requires.txt
caddiepy.egg-info/top_level.txt
caddiepy/examples/__init__.py
caddiepy/file_utils/download_file.py
caddiepy/file_utils/load_file.py
caddiepy/utils/statistics.py