Metadata-Version: 2.1
Name: caddiepy
Version: 0.3.0
Summary: The python package to the Cancer Driver Drug Interaction Explorer (CADDIE)
Home-page: http://pypi.python.org/pypi/caddiepy/
Author: Maiykol
Author-email: michael.hartung@uni-hamburg.de
License: LICENSE
Platform: UNKNOWN
Classifier: Development Status :: 3 - Alpha
Classifier: Intended Audience :: Science/Research
Classifier: Programming Language :: Python :: 3.6
Classifier: Programming Language :: Python :: 3.7
Classifier: Programming Language :: Python :: 3.8
Classifier: Programming Language :: Python :: 3.9
